[
    {
        "title": "FAR CRY 6: TRAILER VAZADO MOSTRA AMBIENTE URBANO E DATA DE LANÇAMENTO",
        "url": "/noticias/far-cry-6",
        "thumbnails": [
            {
                "size": "",
                "thumbnail": "https://meups.com.br/wp-content/uploads/2020/05/Ubisoft-1-900x503.jpg"
            }
        ]
    },
    {
        "title": "F1 2020 traz o melhor do automobilismo aos consoles e computador",
        "url": "/noticias/f1-2020",
        "thumbnails": [
            {
                "size": "",
                "thumbnail": "https://img.ibxk.com.br/2020/07/06/06004027194050.jpg"
            }
        ]
    },
    {
        "title": "COMO É ZELDA: BREATH OF THE WILD COM 30 MODS AO MESMO TEMPO? ASSISTA",
        "url": "/noticias/assasins-creed-valhalla",
        "thumbnails": [
            {
                "size": "",
                "thumbnail": "https://img2.ibxk.com.br/2020/07/07/07222405960569.jpg?w=575&h=200&mode=crop"
            }
        ]
    },  
    {
        "title": "PS5 PRETO E VERMELHO É VAZADO EM MATERIAL DA SONY [RUMOR]",
        "url": "/noticias/ps5-preto-vermelho-vazado-material-sony-rumor",
        "thumbnails": [
            {
                "size": "",
                "thumbnail": "https://img.ibxk.com.br///2020/07/10/10111916132072.jpg"
            }
        ]
    }
]

